README.md
README.rst
setup.cfg
setup.py
rdatools/__init__.py
rdatools/constants.py
rdatools/corpus.py
rdatools/discourse.py
rdatools/functions.py
rdatools/pubmed.py
rdatools/tm.py
rdatools/zotero.py
rdatools.egg-info/PKG-INFO
rdatools.egg-info/SOURCES.txt
rdatools.egg-info/dependency_links.txt
rdatools.egg-info/requires.txt
rdatools.egg-info/top_level.txt