Metadata-Version: 1.1
Name: rdatools
Version: 0.1.7
Summary: tools for relational discourse analysis
Home-page: https://github.com/arnosimons/rdatools
Author: Arno Simons
Author-email: UNKNOWN
License: GPLv3
Download-URL: https://github.com/arnosimons/rdatools/archive/0.1.7.tar.gz
Keywords: rdatools,discourse analysis,network analysis,citation analysis,textmining,text processing,zotero,bibliometrics,scientometrics,nlp
Platform: UNKNOWN
Classifier: Development Status :: 3 - Alpha
Classifier: Topic :: Sociology
Classifier: License :: OSI Approved :: GNU General Public License v3 (GPLv3)
Classifier: Programming Language :: Python :: 2.7
